Statistic_Project_2024/TemperatureModel.py
Statistic_Project_2024/__init__.py
Statistic_Project_2024-0.1.dist-info/METADATA
Statistic_Project_2024-0.1.dist-info/WHEEL
Statistic_Project_2024-0.1.dist-info/top_level.txt
Statistic_Project_2024-0.1.dist-info/RECORD
