Metadata-Version: 2.1
Name: Statistic-Project-2024
Version: 0.1
Summary: A package for temperature analysis
Home-page: https://github.com/Said-taoussi/Statistic-Project-2024
Author: Said ETTOUSY
Author-email: said.ETTOUSY@emines.um6p.ma
License: UNKNOWN
Download-URL: https://github.com/Said-taoussi/mStatistic-Project-2024/archive/v0.1.tar.gz
Keywords: temperature,analysis,data
Platform: UNKNOWN
Classifier: Development Status :: 3 - Alpha
Classifier: Intended Audience :: Developers
Classifier: License :: OSI Approved :: MIT License
Classifier: Programming Language :: Python :: 3
Classifier: Programming Language :: Python :: 3.6
Classifier: Programming Language :: Python :: 3.7
Classifier: Programming Language :: Python :: 3.8
Classifier: Programming Language :: Python :: 3.9
Requires-Dist: pandas
Requires-Dist: numpy
Requires-Dist: matplotlib
Requires-Dist: seaborn
Requires-Dist: scipy
Requires-Dist: statsmodels
